<?xml version="1.0" encoding="utf-8" standalone="yes"?>
<Gesture Name="pigtail02" Subject="1" Speed="medium" Number="2" NumPts="97" Millseconds="741" AppName="GestureRecorder" AppVer="1.0.0.0" Date="Tuesday, June 16, 2026" TimeOfDay="03:23:18 PM">
  <Point X="217" Y="417" T="18393777" />
  <Point X="220" Y="418" T="18393791" />
  <Point X="222" Y="419" T="18393806" />
  <Point X="225" Y="419" T="18393815" />
  <Point X="227" Y="419" T="18393822" />
  <Point X="232" Y="419" T="18393829" />
  <Point X="237" Y="419" T="18393837" />
  <Point X="243" Y="419" T="18393846" />
  <Point X="245" Y="419" T="18393853" />
  <Point X="250" Y="418" T="18393859" />
  <Point X="261" Y="414" T="18393867" />
  <Point X="271" Y="410" T="18393874" />
  <Point X="284" Y="405" T="18393883" />
  <Point X="296" Y="398" T="18393890" />
  <Point X="308" Y="391" T="18393897" />
  <Point X="321" Y="383" T="18393905" />
  <Point X="333" Y="374" T="18393912" />
  <Point X="344" Y="365" T="18393919" />
  <Point X="355" Y="354" T="18393927" />
  <Point X="363" Y="343" T="18393935" />
  <Point X="371" Y="332" T="18393942" />
  <Point X="376" Y="323" T="18393950" />
  <Point X="382" Y="312" T="18393958" />
  <Point X="384" Y="304" T="18393965" />
  <Point X="387" Y="295" T="18393974" />
  <Point X="389" Y="286" T="18393979" />
  <Point X="391" Y="277" T="18393986" />
  <Point X="391" Y="269" T="18393994" />
  <Point X="391" Y="261" T="18394001" />
  <Point X="391" Y="252" T="18394009" />
  <Point X="389" Y="242" T="18394016" />
  <Point X="388" Y="232" T="18394024" />
  <Point X="385" Y="224" T="18394032" />
  <Point X="383" Y="219" T="18394039" />
  <Point X="382" Y="216" T="18394047" />
  <Point X="380" Y="213" T="18394054" />
  <Point X="378" Y="212" T="18394062" />
  <Point X="377" Y="210" T="18394069" />
  <Point X="374" Y="208" T="18394077" />
  <Point X="373" Y="207" T="18394084" />
  <Point X="371" Y="206" T="18394091" />
  <Point X="369" Y="206" T="18394099" />
  <Point X="366" Y="206" T="18394106" />
  <Point X="364" Y="206" T="18394114" />
  <Point X="359" Y="206" T="18394122" />
  <Point X="353" Y="206" T="18394129" />
  <Point X="348" Y="207" T="18394137" />
  <Point X="341" Y="210" T="18394144" />
  <Point X="333" Y="214" T="18394151" />
  <Point X="326" Y="219" T="18394159" />
  <Point X="323" Y="220" T="18394166" />
  <Point X="319" Y="222" T="18394174" />
  <Point X="313" Y="226" T="18394181" />
  <Point X="307" Y="231" T="18394189" />
  <Point X="301" Y="236" T="18394196" />
  <Point X="297" Y="240" T="18394204" />
  <Point X="292" Y="245" T="18394211" />
  <Point X="289" Y="249" T="18394219" />
  <Point X="286" Y="253" T="18394226" />
  <Point X="282" Y="259" T="18394234" />
  <Point X="280" Y="265" T="18394242" />
  <Point X="278" Y="270" T="18394249" />
  <Point X="276" Y="277" T="18394256" />
  <Point X="276" Y="284" T="18394264" />
  <Point X="276" Y="293" T="18394271" />
  <Point X="276" Y="301" T="18394279" />
  <Point X="276" Y="309" T="18394290" />
  <Point X="276" Y="318" T="18394294" />
  <Point X="278" Y="327" T="18394301" />
  <Point X="280" Y="334" T="18394309" />
  <Point X="284" Y="341" T="18394316" />
  <Point X="288" Y="349" T="18394324" />
  <Point X="293" Y="356" T="18394332" />
  <Point X="298" Y="364" T="18394339" />
  <Point X="303" Y="371" T="18394347" />
  <Point X="308" Y="379" T="18394354" />
  <Point X="314" Y="385" T="18394361" />
  <Point X="320" Y="392" T="18394369" />
  <Point X="326" Y="399" T="18394376" />
  <Point X="334" Y="406" T="18394384" />
  <Point X="342" Y="413" T="18394392" />
  <Point X="350" Y="421" T="18394399" />
  <Point X="357" Y="427" T="18394406" />
  <Point X="365" Y="433" T="18394414" />
  <Point X="374" Y="440" T="18394421" />
  <Point X="382" Y="446" T="18394429" />
  <Point X="391" Y="451" T="18394437" />
  <Point X="398" Y="455" T="18394444" />
  <Point X="404" Y="459" T="18394452" />
  <Point X="409" Y="460" T="18394459" />
  <Point X="412" Y="461" T="18394466" />
  <Point X="415" Y="461" T="18394473" />
  <Point X="418" Y="461" T="18394481" />
  <Point X="419" Y="461" T="18394489" />
  <Point X="420" Y="460" T="18394496" />
  <Point X="421" Y="460" T="18394503" />
  <Point X="421" Y="459" T="18394519" />
</Gesture>