<?xml version="1.0" encoding="utf-8" standalone="yes"?>
<Gesture Name="right_sq_bracket06" Subject="1" Speed="medium" Number="6" NumPts="104" Millseconds="1169" AppName="GestureRecorder" AppVer="1.0.0.0" Date="Friday, June 12, 2026" TimeOfDay="02:15:49 PM">
  <Point X="233" Y="206" T="12768639" />
  <Point X="234" Y="206" T="12768684" />
  <Point X="234" Y="205" T="12768692" />
  <Point X="235" Y="205" T="12768721" />
  <Point X="237" Y="205" T="12768736" />
  <Point X="240" Y="205" T="12768744" />
  <Point X="243" Y="205" T="12768751" />
  <Point X="248" Y="205" T="12768759" />
  <Point X="254" Y="205" T="12768767" />
  <Point X="259" Y="205" T="12768774" />
  <Point X="266" Y="207" T="12768782" />
  <Point X="273" Y="209" T="12768789" />
  <Point X="279" Y="210" T="12768797" />
  <Point X="286" Y="211" T="12768804" />
  <Point X="292" Y="211" T="12768812" />
  <Point X="296" Y="212" T="12768819" />
  <Point X="303" Y="213" T="12768827" />
  <Point X="310" Y="213" T="12768834" />
  <Point X="317" Y="213" T="12768842" />
  <Point X="324" Y="213" T="12768849" />
  <Point X="329" Y="213" T="12768857" />
  <Point X="331" Y="213" T="12768864" />
  <Point X="333" Y="213" T="12768872" />
  <Point X="335" Y="213" T="12768879" />
  <Point X="335" Y="214" T="12768999" />
  <Point X="335" Y="216" T="12769014" />
  <Point X="335" Y="219" T="12769021" />
  <Point X="335" Y="221" T="12769031" />
  <Point X="335" Y="226" T="12769036" />
  <Point X="335" Y="233" T="12769044" />
  <Point X="335" Y="240" T="12769051" />
  <Point X="335" Y="242" T="12769059" />
  <Point X="335" Y="249" T="12769067" />
  <Point X="334" Y="256" T="12769074" />
  <Point X="333" Y="264" T="12769082" />
  <Point X="333" Y="273" T="12769089" />
  <Point X="333" Y="283" T="12769097" />
  <Point X="333" Y="293" T="12769104" />
  <Point X="332" Y="305" T="12769111" />
  <Point X="332" Y="316" T="12769119" />
  <Point X="331" Y="327" T="12769126" />
  <Point X="331" Y="337" T="12769134" />
  <Point X="331" Y="345" T="12769141" />
  <Point X="331" Y="353" T="12769149" />
  <Point X="331" Y="360" T="12769156" />
  <Point X="330" Y="366" T="12769164" />
  <Point X="330" Y="371" T="12769171" />
  <Point X="330" Y="375" T="12769186" />
  <Point X="330" Y="383" T="12769190" />
  <Point X="330" Y="388" T="12769202" />
  <Point X="330" Y="395" T="12769209" />
  <Point X="330" Y="403" T="12769217" />
  <Point X="330" Y="410" T="12769224" />
  <Point X="330" Y="415" T="12769231" />
  <Point X="330" Y="417" T="12769239" />
  <Point X="330" Y="419" T="12769246" />
  <Point X="330" Y="420" T="12769254" />
  <Point X="330" Y="421" T="12769262" />
  <Point X="329" Y="422" T="12769269" />
  <Point X="329" Y="423" T="12769276" />
  <Point X="329" Y="425" T="12769284" />
  <Point X="329" Y="427" T="12769299" />
  <Point X="329" Y="428" T="12769306" />
  <Point X="329" Y="429" T="12769314" />
  <Point X="329" Y="430" T="12769322" />
  <Point X="329" Y="431" T="12769329" />
  <Point X="329" Y="432" T="12769344" />
  <Point X="329" Y="433" T="12769389" />
  <Point X="329" Y="434" T="12769419" />
  <Point X="327" Y="434" T="12769531" />
  <Point X="324" Y="434" T="12769535" />
  <Point X="321" Y="434" T="12769546" />
  <Point X="318" Y="432" T="12769554" />
  <Point X="314" Y="431" T="12769562" />
  <Point X="307" Y="429" T="12769569" />
  <Point X="301" Y="428" T="12769576" />
  <Point X="294" Y="425" T="12769584" />
  <Point X="287" Y="424" T="12769591" />
  <Point X="280" Y="422" T="12769599" />
  <Point X="276" Y="421" T="12769606" />
  <Point X="271" Y="420" T="12769615" />
  <Point X="268" Y="420" T="12769621" />
  <Point X="264" Y="419" T="12769629" />
  <Point X="263" Y="419" T="12769636" />
  <Point X="261" Y="419" T="12769644" />
  <Point X="259" Y="419" T="12769651" />
  <Point X="258" Y="419" T="12769666" />
  <Point X="256" Y="419" T="12769674" />
  <Point X="255" Y="419" T="12769681" />
  <Point X="252" Y="419" T="12769689" />
  <Point X="251" Y="419" T="12769696" />
  <Point X="250" Y="419" T="12769705" />
  <Point X="248" Y="419" T="12769711" />
  <Point X="246" Y="419" T="12769719" />
  <Point X="244" Y="419" T="12769726" />
  <Point X="242" Y="419" T="12769734" />
  <Point X="241" Y="419" T="12769742" />
  <Point X="239" Y="419" T="12769749" />
  <Point X="237" Y="420" T="12769757" />
  <Point X="235" Y="420" T="12769771" />
  <Point X="234" Y="420" T="12769779" />
  <Point X="233" Y="422" T="12769787" />
  <Point X="232" Y="422" T="12769802" />
  <Point X="232" Y="423" T="12769809" />
</Gesture>